Workbook

Sheet Charts
A1: HIT SQUAD / PROJECT CONTROLS
A2: Sample Refinery · SAMPLE Boiler Outage PPR · Wood River — Roxana, IL
A3: Cost, Progress & Performance Report
A4: (1) Total Project PPR · Job SAMPLE-2026-017 · 2026 · Wood River — Roxana, IL
A5: Status Date 2026-09-03 · Status: In progress · Prepared by: Hit Squad Project Controls
A6: SAMPLE — synthetic hours and dollars for Look QA. Not a client actual.
A7: Full job cost board — Direct, Indirect, Per diem/travel, Equipment, Rentals, Subs, Materials, hours. PPR field grid follows.
A8: Current Forecast $ | C8: Dollars Expended To Date | E8: Physical % Complete | G8: Hours To Go
A9: ='Total Project PPR'!D29 -> 65135.6 | C9: ='Total Project PPR'!M29 -> 39060 | E9: ='Total Project PPR'!Q29 -> 0.45 | G9: ='Total Project PPR'!T29 -> 242
A70: Steel = live-pack forecast · Amber = Turnip expended · Every major PPR cost lane has a graph. Dense field grid is on Total Project PPR. | X70: board

Sheet Cover
A1: HIT SQUAD / PROJECT CONTROLS
A2: Sample Refinery · SAMPLE Boiler Outage PPR · Wood River — Roxana, IL
A3: Cost, Progress & Performance Report
A4: (1) Total Project PPR · Job SAMPLE-2026-017 · 2026
A5: Status Date 2026-09-03 · Status: In progress · Prepared by: Hit Squad Project Controls
A6: SAMPLE — synthetic hours and dollars for Look QA. Not a client actual.
A8: Field | B8: Detail | D8: PPR snapshot | E8: Value
A9: Client | B9: Sample Refinery | D9: Current Forecast $ | E9: ='Total Project PPR'!D29 -> 65135.6
A10: Job | B10: SAMPLE Boiler Outage PPR | D10: Dollars Expended To Date | E10: ='Total Project PPR'!M29 -> 39060
A11: Site | B11: Wood River — Roxana, IL | D11: Workhours Budget | E11: ='Total Project PPR'!G29 -> 440
A12: Job # | B12: SAMPLE-2026-017 | D12: Hours Expended To Date | E12: ='Total Project PPR'!K29 -> 264
A13: Status Date | B13: 2026-09-03 | D13: Hours Earned To Date | E13: ='Total Project PPR'!O29 -> 198
A14: Estimate status | B14: In progress | D14: Physical % Complete | E14: ='Total Project PPR'!Q29 -> 0.45
A15: Prepared by | B15: Hit Squad Project Controls | D15: Performance To Date | E15: ='Total Project PPR'!S29 -> 0.75
A16: Notes | B16: SAMPLE status — invented hours and dollars only | D16: Hours To Go | E16: ='Total Project PPR'!T29 -> 242
A18: Charts lead the package. Budget from this job’s live estimate pack. Actuals from Turnip T3 Export 15 / 16 through the Status Date. Yellow = Expended. Cyan = Earned.

Sheet Total Project PPR
A1: HIT SQUAD / PROJECT CONTROLS
A2: Sample Refinery · SAMPLE Boiler Outage PPR · Wood River — Roxana, IL
A3: Cost, Progress & Performance Report
A4: (1) Total Project PPR · Job SAMPLE-2026-017 · 2026 · Wood River — Roxana, IL
A5: Status Date 2026-09-03 · Status: In progress · Prepared by: Hit Squad Project Controls · Produced by Hit Squad Project Controls
A6: SAMPLE — synthetic hours and dollars for Look QA. Not a client actual.
B7: Dollars Budget | E7: Workhours Budget | H7: Wage Rate | J7: Work Hours Expended | L7: Dollars Expended | N7: Work Hours Earned | P7: Physical % Complete | R7: Performance
B8: $ | E8: Hrs | H8: $ / Hr | J8: Hrs | L8: $ | N8: Hrs | P8: %
B9: Original | C9: Revised | D9: Current Forecast | E9: Original | F9: Revised | G9: Current Forecast | H9: Budget Rate | I9: Actual Rate | J9: Daily | K9: To Date | L9: Daily | M9: To Date | N9: Daily | O9: To Date | P9: Daily | Q9: To Date | R9: To Go Forecast | S9: To Date | T9: Hours To Go
A10: DIRECT LABOR
A11: Pipefitter Journeyman | B11: 17152.32 | C11: 17152.32 | D11: 17152.32 | E11: 160 | F11: 160 | G11: 160 | H11: =IF(G11=0,0,D11/G11) -> 107.202 | I11: =IF(K11=0,0,M11/K11) -> 105.6 | J11: 60 | K11: 100 | L11: 5280 | M11: 10560 | N11: 24 | O11: 72 | P11: =IF(G11=0,0,N11/G11) -> 0.15 | Q11: =IF(G11=0,0,O11/G11) -> 0.45 | R11: =D11-M11 -> 6592.32 | S11: =IF(K11=0,0,O11/K11) -> 0.72 | T11: =G11-O11 -> 88
A12: Boilermaker Journeyman | B12: 14071.2 | C12: 14071.2 | D12: 14071.2 | E12: 120 | F12: 120 | G12: 120 | H12: =IF(G12=0,0,D12/G12) -> 117.26 | I12: =IF(K12=0,0,M12/K12) -> 116.47059 | J12: 38 | K12: 68 | L12: 3960 | M12: 7920 | N12: 18 | O12: 54 | P12: =IF(G12=0,0,N12/G12) -> 0.15 | Q12: =IF(G12=0,0,O12/G12) -> 0.45 | R12: =D12-M12 -> 6151.2 | S12: =IF(K12=0,0,O12/K12) -> 0.79411765 | T12: =G12-O12 -> 66
A13: Subtotal Direct Labor | B13: =SUM(B11,B12) -> 31223.52 | C13: =SUM(C11,C12) -> 31223.52 | D13: =SUM(D11,D12) -> 31223.52 | E13: =SUM(E11,E12) -> 280 | F13: =SUM(F11,F12) -> 280 | G13: =SUM(G11,G12) -> 280 | H13: =IF(G13=0,0,D13/G13) -> 111.51257 | I13: =IF(K13=0,0,M13/K13) -> 110 | J13: =SUM(J11,J12) -> 98 | K13: =SUM(K11,K12) -> 168 | L13: =SUM(L11,L12) -> 9240 | M13: =SUM(M11,M12) -> 18480 | N13: =SUM(N11,N12) -> 42 | O13: =SUM(O11,O12) -> 126 | P13: =IF(G13=0,0,N13/G13) -> 0.15 | Q13: =IF(G13=0,0,O13/G13) -> 0.45 | R13: =D13-M13 -> 12743.52 | S13: =IF(K13=0,0,O13/K13) -> 0.75 | T13: =G13-O13 -> 154
A14: INDIRECT LABOR
A15: Foremen | B15: 4548.96 | C15: 4548.96 | D15: 4548.96 | E15: 40 | F15: 40 | G15: 40 | H15: =IF(G15=0,0,D15/G15) -> 113.724 | I15: =IF(K15=0,0,M15/K15) -> 130 | J15: 12 | K15: 24 | L15: 1560 | M15: 3120 | N15: 9.6 | O15: 18 | P15: =IF(G15=0,0,N15/G15) -> 0.24 | Q15: =IF(G15=0,0,O15/G15) -> 0.45 | R15: =D15-M15 -> 1428.96 | S15: =IF(K15=0,0,O15/K15) -> 0.75 | T15: =G15-O15 -> 22
A16: Support | B16: 0 | C16: 0 | D16: 0 | E16: 80 | F16: 80 | G16: 80 | H16: =IF(G16=0,0,D16/G16) -> 0 | I16: =IF(K16=0,0,M16/K16) -> 80 | J16: 24 | K16: 48 | L16: 1920 | M16: 3840 | N16: 19.2 | O16: 36 | P16: =IF(G16=0,0,N16/G16) -> 0.24 | Q16: =IF(G16=0,0,O16/G16) -> 0.45 | R16: =D16-M16 -> -3840 | S16: =IF(K16=0,0,O16/K16) -> 0.75 | T16: =G16-O16 -> 44
A17: Staff | B17: 4823.12 | C17: 4823.12 | D17: 4823.12 | E17: 40 | F17: 40 | G17: 40 | H17: =IF(G17=0,0,D17/G17) -> 120.578 | I17: =IF(K17=0,0,M17/K17) -> 150 | J17: 12 | K17: 24 | L17: 1800 | M17: 3600 | N17: 9.6 | O17: 18 | P17: =IF(G17=0,0,N17/G17) -> 0.24 | Q17: =IF(G17=0,0,O17/G17) -> 0.45 | R17: =D17-M17 -> 1223.12 | S17: =IF(K17=0,0,O17/K17) -> 0.75 | T17: =G17-O17 -> 22
A18: Per Diem | B18: 2640 | C18: 2640 | D18: 2640 | E18: 0 | F18: 0 | G18: 0 | H18: =IF(G18=0,0,D18/G18) -> 0 | I18: =IF(K18=0,0,M18/K18) -> 0 | J18: 0 | K18: 0 | L18: 910 | M18: 1820 | N18: 0 | O18: 0 | P18: =IF(G18=0,0,N18/G18) -> 0 | Q18: =IF(G18=0,0,O18/G18) -> 0 | R18: =D18-M18 -> 820 | S18: =IF(K18=0,0,O18/K18) -> 0 | T18: =G18-O18 -> 0
A19: Mileage / Travel | B19: 280 | C19: 280 | D19: 280 | E19: 0 | F19: 0 | G19: 0 | H19: =IF(G19=0,0,D19/G19) -> 0 | I19: =IF(K19=0,0,M19/K19) -> 0 | J19: 0 | K19: 0 | L19: 0 | M19: 0 | N19: 0 | O19: 0 | P19: =IF(G19=0,0,N19/G19) -> 0 | Q19: =IF(G19=0,0,O19/G19) -> 0 | R19: =D19-M19 -> 280 | S19: =IF(K19=0,0,O19/K19) -> 0 | T19: =G19-O19 -> 0
A20: Weather Delays | B20: 0 | C20: 0 | D20: 0 | E20: 0 | F20: 0 | G20: 0 | H20: =IF(G20=0,0,D20/G20) -> 0 | I20: =IF(K20=0,0,M20/K20) -> 0 | J20: 0 | K20: 0 | L20: 0 | M20: 0 | N20: 0 | O20: 0 | P20: =IF(G20=0,0,N20/G20) -> 0 | Q20: =IF(G20=0,0,O20/G20) -> 0 | R20: =D20-M20 -> 0 | S20: =IF(K20=0,0,O20/K20) -> 0 | T20: =G20-O20 -> 0
A21: Onboarding | B21: 0 | C21: 0 | D21: 0 | E21: 0 | F21: 0 | G21: 0 | H21: =IF(G21=0,0,D21/G21) -> 0 | I21: =IF(K21=0,0,M21/K21) -> 0 | J21: 0 | K21: 0 | L21: 0 | M21: 0 | N21: 0 | O21: 0 | P21: =IF(G21=0,0,N21/G21) -> 0 | Q21: =IF(G21=0,0,O21/G21) -> 0 | R21: =D21-M21 -> 0 | S21: =IF(K21=0,0,O21/K21) -> 0 | T21: =G21-O21 -> 0
A22: Subtotal Labor / PD | B22: =SUM(B11,B12,B15,B16,B17,B18,B19,B20,B21) -> 43515.6 | C22: =SUM(C11,C12,C15,C16,C17,C18,C19,C20,C21) -> 43515.6 | D22: =SUM(D11,D12,D15,D16,D17,D18,D19,D20,D21) -> 43515.6 | E22: =SUM(E11,E12,E15,E16,E17,E18,E19,E20,E21) -> 440 | F22: =SUM(F11,F12,F15,F16,F17,F18,F19,F20,F21) -> 440 | G22: =SUM(G11,G12,G15,G16,G17,G18,G19,G20,G21) -> 440 | H22: =IF(G22=0,0,D22/G22) -> 98.899091 | I22: =IF(K22=0,0,M22/K22) -> 116.89394 | J22: =SUM(J11,J12,J15,J16,J17,J18,J19,J20,J21) -> 146 | K22: =SUM(K11,K12,K15,K16,K17,K18,K19,K20,K21) -> 264 | L22: =SUM(L11,L12,L15,L16,L17,L18,L19,L20,L21) -> 15430 | M22: =SUM(M11,M12,M15,M16,M17,M18,M19,M20,M21) -> 30860 | N22: =SUM(N11,N12,N15,N16,N17,N18,N19,N20,N21) -> 80.4 | O22: =SUM(O11,O12,O15,O16,O17,O18,O19,O20,O21) -> 198 | P22: =IF(G22=0,0,N22/G22) -> 0.18272727 | Q22: =IF(G22=0,0,O22/G22) -> 0.45 | R22: =D22-M22 -> 12655.6 | S22: =IF(K22=0,0,O22/K22) -> 0.75 | T22: =G22-O22 -> 242
A23: MATERIALS & SUBCONTRACTS
A24: Materials | B24: 1020 | C24: 1020 | D24: 1020 | E24: 0 | F24: 0 | G24: 0 | H24: =IF(G24=0,0,D24/G24) -> 0 | I24: =IF(K24=0,0,M24/K24) -> 0 | J24: 0 | K24: 0 | L24: 0 | M24: 0 | N24: 0 | O24: 0 | P24: =IF(G24=0,0,N24/G24) -> 0 | Q24: =IF(G24=0,0,O24/G24) -> 0 | R24: =D24-M24 -> 1020 | S24: =IF(K24=0,0,O24/K24) -> 0 | T24: =G24-O24 -> 0
A25: Company Owned Equipment | B25: 0 | C25: 0 | D25: 0 | E25: 0 | F25: 0 | G25: 0 | H25: =IF(G25=0,0,D25/G25) -> 0 | I25: =IF(K25=0,0,M25/K25) -> 0 | J25: 0 | K25: 0 | L25: 0 | M25: 0 | N25: 0 | O25: 0 | P25: =IF(G25=0,0,N25/G25) -> 0 | Q25: =IF(G25=0,0,O25/G25) -> 0 | R25: =D25-M25 -> 0 | S25: =IF(K25=0,0,O25/K25) -> 0 | T25: =G25-O25 -> 0
A26: Subcontractors | B26: 18200 | C26: 18200 | D26: 18200 | E26: 0 | F26: 0 | G26: 0 | H26: =IF(G26=0,0,D26/G26) -> 0 | I26: =IF(K26=0,0,M26/K26) -> 0 | J26: 0 | K26: 0 | L26: 4100 | M26: 8200 | N26: 0 | O26: 0 | P26: =IF(G26=0,0,N26/G26) -> 0 | Q26: =IF(G26=0,0,O26/G26) -> 0 | R26: =D26-M26 -> 10000 | S26: =IF(K26=0,0,O26/K26) -> 0 | T26: =G26-O26 -> 0
A27: 3rd Party General Rentals | B27: 2400 | C27: 2400 | D27: 2400 | E27: 0 | F27: 0 | G27: 0 | H27: =IF(G27=0,0,D27/G27) -> 0 | I27: =IF(K27=0,0,M27/K27) -> 0 | J27: 0 | K27: 0 | L27: 0 | M27: 0 | N27: 0 | O27: 0 | P27: =IF(G27=0,0,N27/G27) -> 0 | Q27: =IF(G27=0,0,O27/G27) -> 0 | R27: =D27-M27 -> 2400 | S27: =IF(K27=0,0,O27/K27) -> 0 | T27: =G27-O27 -> 0
A28: Subtotal Material & Subcontracts | B28: =SUM(B24,B25,B26,B27) -> 21620 | C28: =SUM(C24,C25,C26,C27) -> 21620 | D28: =SUM(D24,D25,D26,D27) -> 21620 | E28: =SUM(E24,E25,E26,E27) -> 0 | F28: =SUM(F24,F25,F26,F27) -> 0 | G28: =SUM(G24,G25,G26,G27) -> 0 | H28: =IF(G28=0,0,D28/G28) -> 0 | I28: =IF(K28=0,0,M28/K28) -> 0 | J28: =SUM(J24,J25,J26,J27) -> 0 | K28: =SUM(K24,K25,K26,K27) -> 0 | L28: =SUM(L24,L25,L26,L27) -> 4100 | M28: =SUM(M24,M25,M26,M27) -> 8200 | N28: =SUM(N24,N25,N26,N27) -> 0 | O28: =SUM(O24,O25,O26,O27) -> 0 | P28: =IF(G28=0,0,N28/G28) -> 0 | Q28: =IF(G28=0,0,O28/G28) -> 0 | R28: =D28-M28 -> 13420 | S28: =IF(K28=0,0,O28/K28) -> 0 | T28: =G28-O28 -> 0
A29: TOTAL PROJECT | B29: =SUM(B22,B28) -> 65135.6 | C29: =SUM(C22,C28) -> 65135.6 | D29: =SUM(D22,D28) -> 65135.6 | E29: =SUM(E22,E28) -> 440 | F29: =SUM(F22,F28) -> 440 | G29: =SUM(G22,G28) -> 440 | H29: =IF(G29=0,0,D29/G29) -> 148.03545 | I29: =IF(K29=0,0,M29/K29) -> 147.95455 | J29: =SUM(J22,J28) -> 146 | K29: =SUM(K22,K28) -> 264 | L29: =SUM(L22,L28) -> 19530 | M29: =SUM(M22,M28) -> 39060 | N29: =SUM(N22,N28) -> 80.4 | O29: =SUM(O22,O28) -> 198 | P29: =IF(G29=0,0,N29/G29) -> 0.18272727 | Q29: =IF(G29=0,0,O29/G29) -> 0.45 | R29: =D29-M29 -> 26075.6 | S29: =IF(K29=0,0,O29/K29) -> 0.75 | T29: =G29-O29 -> 242
A31: Notes | B31: SAMPLE status — invented hours and dollars only · Earned Mhr from 01 DailyReport_TOTAL KPI on Cost report (Summary Phase Grand Total). Physical % = earned / Direct budget hours (hours win if Earned % was also typed). Support earned = Direct % × Support budget hours. Budget from the live Hit Squad estimate pack — not Mike’s Estimate Summary links.

Sheet Hrs S-curve
A1: HIT SQUAD / PROJECT CONTROLS
A2: Sample Refinery · SAMPLE Boiler Outage PPR · Wood River — Roxana, IL
A3: Hours S-curve · steel = live-pack estimate · amber = T3 Export 16 spent
A6: Date | B6: Est hours | C6: Act hours | D6: Cum est hours | E6: Cum act hours | F6: Est headcount | G6: Act headcount
A7: 2026-09-01 | B7: 90 | C7: 90 | D7: =B7 -> 90 | E7: =C7 -> 90 | F7: 9 | G7: 9
A8: 2026-09-02 | B8: 90 | C8: 90 | D8: =D7+B8 -> 180 | E8: =E7+C8 -> 180 | F8: 9 | G8: 9
A9: 2026-09-03 | B9: 90 | C9: 36 | D9: =D8+B9 -> 270 | E9: =E8+C9 -> 216 | F9: 9 | G9: 4
A10: 2026-09-04 | B10: 90 | C10: 0 | D10: =D9+B10 -> 360 | E10: =E9+C10 -> 216 | F10: 9 | G10: 0
A12: Cumulative hours — estimate vs actuals
A28: Steel = live-pack estimate · Amber = T3 Export 16 Units · chart-ready columns D / E

Sheet Report log
A1: HIT SQUAD / PROJECT CONTROLS
A2: Sample Refinery · SAMPLE Boiler Outage PPR · Wood River — Roxana, IL
A3: Dated daily report log
A6: Status date | B6: Saved | C6: Forecast $ | D6: Expended $ | E6: Budget hours | F6: Expended hours | G6: Notes
A7: 2026-09-03 | B7: 1970-01-01 00:00:00 | C7: 66540.9 | D7: 39060 | E7: 360 | F7: 264 | G7: SAMPLE status — invented hours and dollars only
A8: 2026-09-01 | B8: 1970-01-01 00:00:00 | C8: 66540.9 | D8: 19530 | E8: 360 | F8: 132 | G8: SAMPLE day 1 — synthetic Turnip paste

Sheet T3 Export 15
A1: HIT SQUAD / PROJECT CONTROLS
A2: Sample Refinery · SAMPLE Boiler Outage PPR · Wood River — Roxana, IL
A3: T3 Export 15 — Client Cost Analysis · Status Date 2026-09-03
A6: ChargeCode | B6: WO_Description | C6: LaborTotal_ClientActual_Units | D6: LaborTotal_ClientActual_Dollars | E6: PD_ClientActual_Dollars | F6: Other_ClientActual_Units | G6: TotalDollars_ClientActual
A7: 100 | B7: Direct Labor | C7: 168 | D7: 18480 | E7: 0 | F7: 0 | G7: 18480
A8: 400 | B8: Foremen | C8: 24 | D8: 3120 | E8: 0 | F8: 0 | G8: 3120
A9: 500 | B9: Support | C9: 48 | D9: 3840 | E9: 0 | F9: 0 | G9: 3840
A10: 505 | B10: Per Diem | C10: 0 | D10: 0 | E10: 1820 | F10: 0 | G10: 1820
A11: 702 | B11: Staff | C11: 24 | D11: 3600 | E11: 0 | F11: 0 | G11: 3600
A12: 721 | B12: Materials | C12: 0 | D12: 0 | E12: 0 | F12: 12 | G12: 980
A13: 725 | B13: 3rd Party General Rentals | C13: 0 | D13: 0 | E13: 0 | F13: 1 | G13: 2100
A14: 727 | B14: Company Owned Equipment | C14: 0 | D14: 0 | E14: 0 | F14: 2 | G14: 1600
A15: 730 | B15: Subcontractors | C15: 0 | D15: 8200 | E15: 0 | F15: 0 | G15: 8200

Sheet T3 Export 16
A1: HIT SQUAD / PROJECT CONTROLS
A2: Sample Refinery · SAMPLE Boiler Outage PPR · Wood River — Roxana, IL
A3: T3 Export 16 — Client Craft Analysis · Status Date 2026-09-03
A6: event_dt | B6: craft | C6: employee | D6: Units | E6: ST_Units | F6: OT_Units | G6: DT_Units | H6: ChargeCode | I6: Headcount
A7: 2026-09-01 | B7: Pipefitter Journeyman | C7: SAMPLE-101 | D7: 40 | E7: 32 | F7: 8 | G7: 0 | H7: 100 | I7: 4
A8: 2026-09-01 | B8: Boilermaker Journeyman | C8: SAMPLE-201 | D8: 30 | E8: 24 | F8: 6 | G8: 0 | H8: 100 | I8: 3
A9: 2026-09-01 | B9: Firewatch | C9: SAMPLE-301 | D9: 20 | E9: 16 | F9: 4 | G9: 0 | H9: 500 | I9: 2
A10: 2026-09-02 | B10: Pipefitter Journeyman | C10: SAMPLE-101 | D10: 40 | E10: 32 | F10: 8 | G10: 0 | H10: 100 | I10: 4
A11: 2026-09-02 | B11: Boilermaker Journeyman | C11: SAMPLE-201 | D11: 30 | E11: 24 | F11: 6 | G11: 0 | H11: 100 | I11: 3
A12: 2026-09-02 | B12: Firewatch | C12: SAMPLE-301 | D12: 20 | E12: 16 | F12: 4 | G12: 0 | H12: 500 | I12: 2
A13: 2026-09-03 | B13: Pipefitter Journeyman | C13: SAMPLE-101 | D13: 20 | E13: 16 | F13: 4 | G13: 0 | H13: 100 | I13: 2
A14: 2026-09-03 | B14: Boilermaker Journeyman | C14: SAMPLE-201 | D14: 8 | E14: 8 | F14: 0 | G14: 0 | H14: 100 | I14: 1
A15: 2026-09-03 | B15: Firewatch | C15: SAMPLE-301 | D15: 8 | E15: 8 | F15: 0 | G15: 0 | H15: 500 | I15: 1

Sheet _ChartData
A1: HIT SQUAD / PROJECT CONTROLS
A2: Chart source — hidden helper
A3: Ranges referenced by the Charts dashboard and Hrs S-curve.
A6: Vendor | B6: Amount | D6: Cost element | E6: Forecast $ | F6: Expended $ | H6: Direct craft | I6: Forecast $ | J6: Expended $ | L6: Indirect | M6: Forecast $ | N6: Expended $ | P6: Per diem / travel | Q6: Forecast $ | R6: Expended $ | T6: Equipment / rentals | U6: Forecast $ | V6: Expended $ | X6: Materials / other | Y6: Forecast $ | Z6: Expended $ | AB6: Craft | AC6: Hours | AD6: Headcount
A7: SAMPLE NDE | B7: 6500 | D7: Direct Labor | E7: ='Total Project PPR'!D13 -> 31223.52 | F7: ='Total Project PPR'!M13 -> 18480 | H7: Pipefitter Journeyman | I7: ='Total Project PPR'!D11 -> 17152.32 | J7: ='Total Project PPR'!M11 -> 10560 | L7: Foremen | M7: ='Total Project PPR'!D15 -> 4548.96 | N7: ='Total Project PPR'!M15 -> 3120 | P7: Per Diem | Q7: ='Total Project PPR'!D18 -> 2640 | R7: ='Total Project PPR'!M18 -> 1820 | T7: Company Owned Equipment | U7: ='Total Project PPR'!D25 -> 0 | V7: ='Total Project PPR'!M25 -> 0 | X7: Materials | Y7: ='Total Project PPR'!D24 -> 1020 | Z7: ='Total Project PPR'!M24 -> 0 | AB7: Pipefitter Journeyman | AC7: 100 | AD7: 4
A8: SAMPLE Insulation | B8: 4200 | D8: Indirect labor | E8: =SUM('Total Project PPR'!D15,'Total Project PPR'!D16,'Total Project PPR'!D17) -> 9372.08 | F8: =SUM('Total Project PPR'!M15,'Total Project PPR'!M16,'Total Project PPR'!M17) -> 10560 | H8: Boilermaker Journeyman | I8: ='Total Project PPR'!D12 -> 14071.2 | J8: ='Total Project PPR'!M12 -> 7920 | L8: Support | M8: ='Total Project PPR'!D16 -> 0 | N8: ='Total Project PPR'!M16 -> 3840 | P8: Mileage / Travel | Q8: ='Total Project PPR'!D19 -> 280 | R8: ='Total Project PPR'!M19 -> 0 | T8: 3rd Party Rentals | U8: ='Total Project PPR'!D27 -> 2400 | V8: ='Total Project PPR'!M27 -> 0 | X8: Weather Delays | Y8: ='Total Project PPR'!D20 -> 0 | Z8: ='Total Project PPR'!M20 -> 0 | AB8: Boilermaker Journeyman | AC8: 68 | AD8: 3
A9: SAMPLE Scaffold | B9: 3800 | D9: Per diem / travel | E9: =SUM('Total Project PPR'!D18,'Total Project PPR'!D19) -> 2920 | F9: =SUM('Total Project PPR'!M18,'Total Project PPR'!M19) -> 1820 | L9: Staff | M9: ='Total Project PPR'!D17 -> 4823.12 | N9: ='Total Project PPR'!M17 -> 3600 | X9: Onboarding | Y9: ='Total Project PPR'!D21 -> 0 | Z9: ='Total Project PPR'!M21 -> 0 | AB9: Firewatch | AC9: 48 | AD9: 2
A10: SAMPLE Crane | B10: 3700 | D10: Equipment (COE) | E10: ='Total Project PPR'!D25 -> 0 | F10: ='Total Project PPR'!M25 -> 0
D11: 3rd Party Rentals | E11: ='Total Project PPR'!D27 -> 2400 | F11: ='Total Project PPR'!M27 -> 0
D12: Subcontractors | E12: ='Total Project PPR'!D26 -> 18200 | F12: ='Total Project PPR'!M26 -> 8200
D13: Materials / other | E13: =SUM('Total Project PPR'!D24,'Total Project PPR'!D20,'Total Project PPR'!D21) -> 1020 | F13: =SUM('Total Project PPR'!M24,'Total Project PPR'!M20,'Total Project PPR'!M21) -> 0
